flicker/__init__.py
flicker/column.py
flicker/dataframe.py
flicker/group.py
flicker/mkname.py
flicker/recipes.py
flicker/summary.py
flicker/udf.py
flicker/utils.py
flicker/variables.py
flicker/version.py
flicker/reshape/__init__.py
flicker/reshape/concat.py
flicker-1.2.0.dist-info/METADATA
flicker-1.2.0.dist-info/WHEEL
flicker-1.2.0.dist-info/licenses/LICENSE
flicker-1.2.0.dist-info/RECORD
