Metadata-Version: 2.4
Name: flicker
Version: 1.2.0
Summary: Provides FlickerDataFrame, a wrapper over Pyspark DataFrame to provide a pandas-like API
Project-URL: Homepage, https://github.com/ankur-gupta/flicker
Project-URL: Repository, https://github.com/ankur-gupta/flicker.git
Author-email: Flicker Contributors <7110058+ankur-gupta@users.noreply.github.com>
License-Expression: Apache-2.0
License-File: LICENSE
Keywords: API,dataframe,pandas,pyspark,spark,wrapper
Classifier: Development Status :: 4 - Beta
Classifier: License :: OSI Approved :: Apache Software License
Classifier: Operating System :: OS Independent
Classifier: Programming Language :: Python :: 3
Requires-Python: >=3.9
Requires-Dist: numpy
Requires-Dist: pandas
Requires-Dist: pyarrow>=4.0.0
Requires-Dist: pyspark>=3.4.1
Requires-Dist: setuptools
